[
    {
        "_id": "5b5edb03fa7f604fd1d1721a",
        "libs": [
            {
                "branch": "master",
                "commit": "f55cea00df918cd515ae1bf7069f0d1fc0940a9a",
                "datetime": "2018/07/30-11:07:37",
                "name": "bench-stat",
                "timestamp": 1532941657
            }
        ],
        "problem": {
            "application": "bench-stat",
            "case-name": "cache",
            "test-name": "memory"
        },
        "result": {
            "duration": 12.7840185165405
        },
        "system": {
            "hostname": "hybs",
            "metric": "foobar",
            "name": "Linux",
            "os_name": "18.04 LTS (Bionic Beaver)",
            "os_version": "Ubuntu",
            "test-id": 0,
            "test-name": "memory-cache-test-all",
            "username": "jan-hybs:1000:1000"
        },
        "timers": [
            {
                "duration": 1.45733511447906,
                "name": "mem_l1"
            },
            {
                "duration": 3.48087692260742,
                "name": "mem_l2"
            },
            {
                "duration": 7.84579610824585,
                "name": "mem_l3"
            }
        ]
    },
    {
        "_id": "5b5edb0ffa7f604fd1d1721b",
        "libs": [
            {
                "branch": "master",
                "commit": "f55cea00df918cd515ae1bf7069f0d1fc0940a9a",
                "datetime": "2018/07/30-11:07:37",
                "name": "bench-stat",
                "timestamp": 1532941657
            }
        ],
        "problem": {
            "application": "bench-stat",
            "case-name": "cache",
            "test-name": "memory"
        },
        "result": {
            "duration": 12.731858253479
        },
        "system": {
            "hostname": "hybs",
            "metric": "foobar",
            "name": "Linux",
            "os_name": "18.04 LTS (Bionic Beaver)",
            "os_version": "Ubuntu",
            "test-id": 0,
            "test-name": "memory-cache-test-all",
            "username": "jan-hybs:1000:1000"
        },
        "timers": [
            {
                "duration": 1.46168208122253,
                "name": "mem_l1"
            },
            {
                "duration": 3.48420000076294,
                "name": "mem_l2"
            },
            {
                "duration": 7.78596544265747,
                "name": "mem_l3"
            }
        ]
    },
    {
        "_id": "5b5edb1cfa7f604fd1d1721c",
        "libs": [
            {
                "branch": "master",
                "commit": "f55cea00df918cd515ae1bf7069f0d1fc0940a9a",
                "datetime": "2018/07/30-11:07:37",
                "name": "bench-stat",
                "timestamp": 1532941657
            }
        ],
        "problem": {
            "application": "bench-stat",
            "case-name": "cache",
            "test-name": "memory"
        },
        "result": {
            "duration": 12.7912788391113
        },
        "system": {
            "hostname": "hybs",
            "metric": "foobar",
            "name": "Linux",
            "os_name": "18.04 LTS (Bionic Beaver)",
            "os_version": "Ubuntu",
            "test-id": 0,
            "test-name": "memory-cache-test-all",
            "username": "jan-hybs:1000:1000"
        },
        "timers": [
            {
                "duration": 1.45944941043854,
                "name": "mem_l1"
            },
            {
                "duration": 3.48426342010498,
                "name": "mem_l2"
            },
            {
                "duration": 7.84755516052246,
                "name": "mem_l3"
            }
        ]
    },
    {
        "_id": "5b5edb29fa7f604fd1d1721d",
        "libs": [
            {
                "branch": "master",
                "commit": "f55cea00df918cd515ae1bf7069f0d1fc0940a9a",
                "datetime": "2018/07/30-11:07:37",
                "name": "bench-stat",
                "timestamp": 1532941657
            }
        ],
        "problem": {
            "application": "bench-stat",
            "case-name": "cache",
            "test-name": "memory"
        },
        "result": {
            "duration": 12.7536191940308
        },
        "system": {
            "hostname": "hybs",
            "metric": "foobar",
            "name": "Linux",
            "os_name": "18.04 LTS (Bionic Beaver)",
            "os_version": "Ubuntu",
            "test-id": 0,
            "test-name": "memory-cache-test-all",
            "username": "jan-hybs:1000:1000"
        },
        "timers": [
            {
                "duration": 1.46473515033722,
                "name": "mem_l1"
            },
            {
                "duration": 3.48772406578064,
                "name": "mem_l2"
            },
            {
                "duration": 7.80114889144897,
                "name": "mem_l3"
            }
        ]
    },
    {
        "_id": "5b5edb36fa7f604fd1d1721e",
        "libs": [
            {
                "branch": "master",
                "commit": "f55cea00df918cd515ae1bf7069f0d1fc0940a9a",
                "datetime": "2018/07/30-11:07:37",
                "name": "bench-stat",
                "timestamp": 1532941657
            }
        ],
        "problem": {
            "application": "bench-stat",
            "case-name": "cache",
            "test-name": "memory"
        },
        "result": {
            "duration": 12.8362998962402
        },
        "system": {
            "hostname": "hybs",
            "metric": "foobar",
            "name": "Linux",
            "os_name": "18.04 LTS (Bionic Beaver)",
            "os_version": "Ubuntu",
            "test-id": 0,
            "test-name": "memory-cache-test-all",
            "username": "jan-hybs:1000:1000"
        },
        "timers": [
            {
                "duration": 1.46056163311005,
                "name": "mem_l1"
            },
            {
                "duration": 3.48525619506836,
                "name": "mem_l2"
            },
            {
                "duration": 7.8904709815979,
                "name": "mem_l3"
            }
        ]
    },
    {
        "_id": "5b5edb43fa7f604fd1d1721f",
        "libs": [
            {
                "branch": "master",
                "commit": "f55cea00df918cd515ae1bf7069f0d1fc0940a9a",
                "datetime": "2018/07/30-11:07:37",
                "name": "bench-stat",
                "timestamp": 1532941657
            }
        ],
        "problem": {
            "application": "bench-stat",
            "case-name": "cache",
            "test-name": "memory"
        },
        "result": {
            "duration": 12.7604846954346
        },
        "system": {
            "hostname": "hybs",
            "metric": "foobar",
            "name": "Linux",
            "os_name": "18.04 LTS (Bionic Beaver)",
            "os_version": "Ubuntu",
            "test-id": 0,
            "test-name": "memory-cache-test-all",
            "username": "jan-hybs:1000:1000"
        },
        "timers": [
            {
                "duration": 1.46845161914825,
                "name": "mem_l1"
            },
            {
                "duration": 3.49449634552002,
                "name": "mem_l2"
            },
            {
                "duration": 7.79752492904663,
                "name": "mem_l3"
            }
        ]
    },
    {
        "_id": "5b5edb50fa7f604fd1d17220",
        "libs": [
            {
                "branch": "master",
                "commit": "f55cea00df918cd515ae1bf7069f0d1fc0940a9a",
                "datetime": "2018/07/30-11:07:37",
                "name": "bench-stat",
                "timestamp": 1532941657
            }
        ],
        "problem": {
            "application": "bench-stat",
            "case-name": "cache",
            "test-name": "memory"
        },
        "result": {
            "duration": 12.9499578475952
        },
        "system": {
            "hostname": "hybs",
            "metric": "foobar",
            "name": "Linux",
            "os_name": "18.04 LTS (Bionic Beaver)",
            "os_version": "Ubuntu",
            "test-id": 0,
            "test-name": "memory-cache-test-all",
            "username": "jan-hybs:1000:1000"
        },
        "timers": [
            {
                "duration": 1.47236907482147,
                "name": "mem_l1"
            },
            {
                "duration": 3.56529521942139,
                "name": "mem_l2"
            },
            {
                "duration": 7.91228199005127,
                "name": "mem_l3"
            }
        ]
    },
    {
        "_id": "5b5edc3bfa7f6051ba416775",
        "libs": [
            {
                "branch": "master",
                "commit": "332f41999823926cca70b0afcdeb51282ceae7a5",
                "datetime": "2018/07/30-11:36:22",
                "name": "bench-stat",
                "timestamp": 1532943382
            }
        ],
        "problem": {
            "application": "bench-stat",
            "case-name": "cache",
            "test-name": "memory"
        },
        "result": {
            "duration": 12.542067527771
        },
        "system": {
            "hostname": "hybs",
            "metric": "foobar",
            "name": "Linux",
            "os_name": "18.04 LTS (Bionic Beaver)",
            "os_version": "Ubuntu",
            "test-id": 0,
            "test-name": "memory-cache-test-all",
            "username": "jan-hybs:1000:1000"
        },
        "timers": [
            {
                "duration": 1.4609249830246,
                "name": "mem_l1"
            },
            {
                "duration": 3.48502779006958,
                "name": "mem_l2"
            },
            {
                "duration": 7.59610366821289,
                "name": "mem_l3"
            }
        ]
    },
    {
        "_id": "5b5edc48fa7f6051ba416776",
        "libs": [
            {
                "branch": "master",
                "commit": "332f41999823926cca70b0afcdeb51282ceae7a5",
                "datetime": "2018/07/30-11:36:22",
                "name": "bench-stat",
                "timestamp": 1532943382
            }
        ],
        "problem": {
            "application": "bench-stat",
            "case-name": "cache",
            "test-name": "memory"
        },
        "result": {
            "duration": 12.634069442749
        },
        "system": {
            "hostname": "hybs",
            "metric": "foobar",
            "name": "Linux",
            "os_name": "18.04 LTS (Bionic Beaver)",
            "os_version": "Ubuntu",
            "test-id": 0,
            "test-name": "memory-cache-test-all",
            "username": "jan-hybs:1000:1000"
        },
        "timers": [
            {
                "duration": 1.49548554420471,
                "name": "mem_l1"
            },
            {
                "duration": 3.48945999145508,
                "name": "mem_l2"
            },
            {
                "duration": 7.64911222457886,
                "name": "mem_l3"
            }
        ]
    },
    {
        "_id": "5b5edc54fa7f6051ba416777",
        "libs": [
            {
                "branch": "master",
                "commit": "332f41999823926cca70b0afcdeb51282ceae7a5",
                "datetime": "2018/07/30-11:36:22",
                "name": "bench-stat",
                "timestamp": 1532943382
            }
        ],
        "problem": {
            "application": "bench-stat",
            "case-name": "cache",
            "test-name": "memory"
        },
        "result": {
            "duration": 12.7473926544189
        },
        "system": {
            "hostname": "hybs",
            "metric": "foobar",
            "name": "Linux",
            "os_name": "18.04 LTS (Bionic Beaver)",
            "os_version": "Ubuntu",
            "test-id": 0,
            "test-name": "memory-cache-test-all",
            "username": "jan-hybs:1000:1000"
        },
        "timers": [
            {
                "duration": 1.46445727348328,
                "name": "mem_l1"
            },
            {
                "duration": 3.53381371498108,
                "name": "mem_l2"
            },
            {
                "duration": 7.74911022186279,
                "name": "mem_l3"
            }
        ]
    },
    {
        "_id": "5b5edc61fa7f6051ba416778",
        "libs": [
            {
                "branch": "master",
                "commit": "332f41999823926cca70b0afcdeb51282ceae7a5",
                "datetime": "2018/07/30-11:36:22",
                "name": "bench-stat",
                "timestamp": 1532943382
            }
        ],
        "problem": {
            "application": "bench-stat",
            "case-name": "cache",
            "test-name": "memory"
        },
        "result": {
            "duration": 12.5837259292603
        },
        "system": {
            "hostname": "hybs",
            "metric": "foobar",
            "name": "Linux",
            "os_name": "18.04 LTS (Bionic Beaver)",
            "os_version": "Ubuntu",
            "test-id": 0,
            "test-name": "memory-cache-test-all",
            "username": "jan-hybs:1000:1000"
        },
        "timers": [
            {
                "duration": 1.4626579284668,
                "name": "mem_l1"
            },
            {
                "duration": 3.48395013809204,
                "name": "mem_l2"
            },
            {
                "duration": 7.6370997428894,
                "name": "mem_l3"
            }
        ]
    },
    {
        "_id": "5b5edc6efa7f6051ba416779",
        "libs": [
            {
                "branch": "master",
                "commit": "332f41999823926cca70b0afcdeb51282ceae7a5",
                "datetime": "2018/07/30-11:36:22",
                "name": "bench-stat",
                "timestamp": 1532943382
            }
        ],
        "problem": {
            "application": "bench-stat",
            "case-name": "cache",
            "test-name": "memory"
        },
        "result": {
            "duration": 12.7661924362183
        },
        "system": {
            "hostname": "hybs",
            "metric": "foobar",
            "name": "Linux",
            "os_name": "18.04 LTS (Bionic Beaver)",
            "os_version": "Ubuntu",
            "test-id": 0,
            "test-name": "memory-cache-test-all",
            "username": "jan-hybs:1000:1000"
        },
        "timers": [
            {
                "duration": 1.48847341537476,
                "name": "mem_l1"
            },
            {
                "duration": 3.53475379943848,
                "name": "mem_l2"
            },
            {
                "duration": 7.74295377731323,
                "name": "mem_l3"
            }
        ]
    },
    {
        "_id": "5b5edc7afa7f6051ba41677a",
        "libs": [
            {
                "branch": "master",
                "commit": "332f41999823926cca70b0afcdeb51282ceae7a5",
                "datetime": "2018/07/30-11:36:22",
                "name": "bench-stat",
                "timestamp": 1532943382
            }
        ],
        "problem": {
            "application": "bench-stat",
            "case-name": "cache",
            "test-name": "memory"
        },
        "result": {
            "duration": 12.7090225219727
        },
        "system": {
            "hostname": "hybs",
            "metric": "foobar",
            "name": "Linux",
            "os_name": "18.04 LTS (Bionic Beaver)",
            "os_version": "Ubuntu",
            "test-id": 0,
            "test-name": "memory-cache-test-all",
            "username": "jan-hybs:1000:1000"
        },
        "timers": [
            {
                "duration": 1.46635782718658,
                "name": "mem_l1"
            },
            {
                "duration": 3.49223256111145,
                "name": "mem_l2"
            },
            {
                "duration": 7.75042057037354,
                "name": "mem_l3"
            }
        ]
    },
    {
        "_id": "5b5edc87fa7f6051ba41677b",
        "libs": [
            {
                "branch": "master",
                "commit": "332f41999823926cca70b0afcdeb51282ceae7a5",
                "datetime": "2018/07/30-11:36:22",
                "name": "bench-stat",
                "timestamp": 1532943382
            }
        ],
        "problem": {
            "application": "bench-stat",
            "case-name": "cache",
            "test-name": "memory"
        },
        "result": {
            "duration": 12.6929731369019
        },
        "system": {
            "hostname": "hybs",
            "metric": "foobar",
            "name": "Linux",
            "os_name": "18.04 LTS (Bionic Beaver)",
            "os_version": "Ubuntu",
            "test-id": 0,
            "test-name": "memory-cache-test-all",
            "username": "jan-hybs:1000:1000"
        },
        "timers": [
            {
                "duration": 1.46217477321625,
                "name": "mem_l1"
            },
            {
                "duration": 3.485267162323,
                "name": "mem_l2"
            },
            {
                "duration": 7.74551963806152,
                "name": "mem_l3"
            }
        ]
    },
    {
        "_id": "5b5edf26fa7f60549ee72bfc",
        "libs": [
            {
                "branch": "master",
                "commit": "95dc53d8ed2f500c436f8d39a77c9ada9d607021",
                "datetime": "2018/07/30-11:48:47",
                "name": "bench-stat",
                "timestamp": 1532944127
            }
        ],
        "problem": {
            "application": "bench-stat",
            "case-name": "cache",
            "test-name": "memory"
        },
        "result": {
            "duration": 14.3110408782959
        },
        "system": {
            "hostname": "hybs",
            "metric": "foobar",
            "name": "Linux",
            "os_name": "18.04 LTS (Bionic Beaver)",
            "os_version": "Ubuntu",
            "test-id": 0,
            "test-name": "memory-cache-test-all",
            "username": "jan-hybs:1000:1000"
        },
        "timers": [
            {
                "duration": 1.49245042800903,
                "name": "mem_l1"
            },
            {
                "duration": 4.37962007522583,
                "name": "mem_l2"
            },
            {
                "duration": 7.83895893096924,
                "name": "mem_l3"
            }
        ]
    },
    {
        "_id": "5b5edf34fa7f60549ee72bfd",
        "libs": [
            {
                "branch": "master",
                "commit": "95dc53d8ed2f500c436f8d39a77c9ada9d607021",
                "datetime": "2018/07/30-11:48:47",
                "name": "bench-stat",
                "timestamp": 1532944127
            }
        ],
        "problem": {
            "application": "bench-stat",
            "case-name": "cache",
            "test-name": "memory"
        },
        "result": {
            "duration": 13.5952987670898
        },
        "system": {
            "hostname": "hybs",
            "metric": "foobar",
            "name": "Linux",
            "os_name": "18.04 LTS (Bionic Beaver)",
            "os_version": "Ubuntu",
            "test-id": 0,
            "test-name": "memory-cache-test-all",
            "username": "jan-hybs:1000:1000"
        },
        "timers": [
            {
                "duration": 1.47610807418823,
                "name": "mem_l1"
            },
            {
                "duration": 4.37292718887329,
                "name": "mem_l2"
            },
            {
                "duration": 7.74625158309937,
                "name": "mem_l3"
            }
        ]
    },
    {
        "_id": "5b5edf42fa7f60549ee72bfe",
        "libs": [
            {
                "branch": "master",
                "commit": "95dc53d8ed2f500c436f8d39a77c9ada9d607021",
                "datetime": "2018/07/30-11:48:47",
                "name": "bench-stat",
                "timestamp": 1532944127
            }
        ],
        "problem": {
            "application": "bench-stat",
            "case-name": "cache",
            "test-name": "memory"
        },
        "result": {
            "duration": 13.6034250259399
        },
        "system": {
            "hostname": "hybs",
            "metric": "foobar",
            "name": "Linux",
            "os_name": "18.04 LTS (Bionic Beaver)",
            "os_version": "Ubuntu",
            "test-id": 0,
            "test-name": "memory-cache-test-all",
            "username": "jan-hybs:1000:1000"
        },
        "timers": [
            {
                "duration": 1.47119975090027,
                "name": "mem_l1"
            },
            {
                "duration": 4.36542940139771,
                "name": "mem_l2"
            },
            {
                "duration": 7.76678562164307,
                "name": "mem_l3"
            }
        ]
    },
    {
        "_id": "5b5edf4ffa7f60549ee72bff",
        "libs": [
            {
                "branch": "master",
                "commit": "95dc53d8ed2f500c436f8d39a77c9ada9d607021",
                "datetime": "2018/07/30-11:48:47",
                "name": "bench-stat",
                "timestamp": 1532944127
            }
        ],
        "problem": {
            "application": "bench-stat",
            "case-name": "cache",
            "test-name": "memory"
        },
        "result": {
            "duration": 13.6042346954346
        },
        "system": {
            "hostname": "hybs",
            "metric": "foobar",
            "name": "Linux",
            "os_name": "18.04 LTS (Bionic Beaver)",
            "os_version": "Ubuntu",
            "test-id": 0,
            "test-name": "memory-cache-test-all",
            "username": "jan-hybs:1000:1000"
        },
        "timers": [
            {
                "duration": 1.46550035476685,
                "name": "mem_l1"
            },
            {
                "duration": 4.36382722854614,
                "name": "mem_l2"
            },
            {
                "duration": 7.7748966217041,
                "name": "mem_l3"
            }
        ]
    },
    {
        "_id": "5b5edf5dfa7f60549ee72c00",
        "libs": [
            {
                "branch": "master",
                "commit": "95dc53d8ed2f500c436f8d39a77c9ada9d607021",
                "datetime": "2018/07/30-11:48:47",
                "name": "bench-stat",
                "timestamp": 1532944127
            }
        ],
        "problem": {
            "application": "bench-stat",
            "case-name": "cache",
            "test-name": "memory"
        },
        "result": {
            "duration": 13.4803581237793
        },
        "system": {
            "hostname": "hybs",
            "metric": "foobar",
            "name": "Linux",
            "os_name": "18.04 LTS (Bionic Beaver)",
            "os_version": "Ubuntu",
            "test-id": 0,
            "test-name": "memory-cache-test-all",
            "username": "jan-hybs:1000:1000"
        },
        "timers": [
            {
                "duration": 1.45944452285767,
                "name": "mem_l1"
            },
            {
                "duration": 4.36849594116211,
                "name": "mem_l2"
            },
            {
                "duration": 7.65240669250488,
                "name": "mem_l3"
            }
        ]
    },
    {
        "_id": "5b5edf6afa7f60549ee72c01",
        "libs": [
            {
                "branch": "master",
                "commit": "95dc53d8ed2f500c436f8d39a77c9ada9d607021",
                "datetime": "2018/07/30-11:48:47",
                "name": "bench-stat",
                "timestamp": 1532944127
            }
        ],
        "problem": {
            "application": "bench-stat",
            "case-name": "cache",
            "test-name": "memory"
        },
        "result": {
            "duration": 13.648138999939
        },
        "system": {
            "hostname": "hybs",
            "metric": "foobar",
            "name": "Linux",
            "os_name": "18.04 LTS (Bionic Beaver)",
            "os_version": "Ubuntu",
            "test-id": 0,
            "test-name": "memory-cache-test-all",
            "username": "jan-hybs:1000:1000"
        },
        "timers": [
            {
                "duration": 1.48771989345551,
                "name": "mem_l1"
            },
            {
                "duration": 4.37754535675049,
                "name": "mem_l2"
            },
            {
                "duration": 7.78286266326904,
                "name": "mem_l3"
            }
        ]
    },
    {
        "_id": "5b5edf78fa7f60549ee72c02",
        "libs": [
            {
                "branch": "master",
                "commit": "95dc53d8ed2f500c436f8d39a77c9ada9d607021",
                "datetime": "2018/07/30-11:48:47",
                "name": "bench-stat",
                "timestamp": 1532944127
            }
        ],
        "problem": {
            "application": "bench-stat",
            "case-name": "cache",
            "test-name": "memory"
        },
        "result": {
            "duration": 13.4956893920898
        },
        "system": {
            "hostname": "hybs",
            "metric": "foobar",
            "name": "Linux",
            "os_name": "18.04 LTS (Bionic Beaver)",
            "os_version": "Ubuntu",
            "test-id": 0,
            "test-name": "memory-cache-test-all",
            "username": "jan-hybs:1000:1000"
        },
        "timers": [
            {
                "duration": 1.46569907665253,
                "name": "mem_l1"
            },
            {
                "duration": 4.3802809715271,
                "name": "mem_l2"
            },
            {
                "duration": 7.64969873428345,
                "name": "mem_l3"
            }
        ]
    },
    {
        "_id": "5b5ee463fa7f60591680d094",
        "libs": [
            {
                "branch": "master",
                "commit": "85e8b641566b01f0d42b98a5b7c638c3777cc4d7",
                "datetime": "2018/07/30-12:11:00",
                "name": "bench-stat",
                "timestamp": 1532945460
            }
        ],
        "problem": {
            "application": "bench-stat",
            "case-name": "cache",
            "test-name": "memory"
        },
        "result": {
            "duration": 13.081748008728
        },
        "system": {
            "hostname": "hybs",
            "metric": "foobar",
            "name": "Linux",
            "os_name": "18.04 LTS (Bionic Beaver)",
            "os_version": "Ubuntu",
            "test-id": 0,
            "test-name": "memory-cache-test-all",
            "username": "jan-hybs:1000:1000"
        },
        "timers": [
            {
                "duration": 1.46395623683929,
                "name": "mem_l1"
            },
            {
                "duration": 3.92149424552917,
                "name": "mem_l2"
            },
            {
                "duration": 7.69628477096558,
                "name": "mem_l3"
            }
        ]
    },
    {
        "_id": "5b5ee470fa7f60591680d095",
        "libs": [
            {
                "branch": "master",
                "commit": "85e8b641566b01f0d42b98a5b7c638c3777cc4d7",
                "datetime": "2018/07/30-12:11:00",
                "name": "bench-stat",
                "timestamp": 1532945460
            }
        ],
        "problem": {
            "application": "bench-stat",
            "case-name": "cache",
            "test-name": "memory"
        },
        "result": {
            "duration": 13.0551166534424
        },
        "system": {
            "hostname": "hybs",
            "metric": "foobar",
            "name": "Linux",
            "os_name": "18.04 LTS (Bionic Beaver)",
            "os_version": "Ubuntu",
            "test-id": 0,
            "test-name": "memory-cache-test-all",
            "username": "jan-hybs:1000:1000"
        },
        "timers": [
            {
                "duration": 1.46391749382019,
                "name": "mem_l1"
            },
            {
                "duration": 3.92249798774719,
                "name": "mem_l2"
            },
            {
                "duration": 7.66868829727173,
                "name": "mem_l3"
            }
        ]
    },
    {
        "_id": "5b5ee47dfa7f60591680d096",
        "libs": [
            {
                "branch": "master",
                "commit": "85e8b641566b01f0d42b98a5b7c638c3777cc4d7",
                "datetime": "2018/07/30-12:11:00",
                "name": "bench-stat",
                "timestamp": 1532945460
            }
        ],
        "problem": {
            "application": "bench-stat",
            "case-name": "cache",
            "test-name": "memory"
        },
        "result": {
            "duration": 13.03258228302
        },
        "system": {
            "hostname": "hybs",
            "metric": "foobar",
            "name": "Linux",
            "os_name": "18.04 LTS (Bionic Beaver)",
            "os_version": "Ubuntu",
            "test-id": 0,
            "test-name": "memory-cache-test-all",
            "username": "jan-hybs:1000:1000"
        },
        "timers": [
            {
                "duration": 1.46585142612457,
                "name": "mem_l1"
            },
            {
                "duration": 3.92492079734802,
                "name": "mem_l2"
            },
            {
                "duration": 7.64178991317749,
                "name": "mem_l3"
            }
        ]
    },
    {
        "_id": "5b5ee48afa7f60591680d097",
        "libs": [
            {
                "branch": "master",
                "commit": "85e8b641566b01f0d42b98a5b7c638c3777cc4d7",
                "datetime": "2018/07/30-12:11:00",
                "name": "bench-stat",
                "timestamp": 1532945460
            }
        ],
        "problem": {
            "application": "bench-stat",
            "case-name": "cache",
            "test-name": "memory"
        },
        "result": {
            "duration": 13.007098197937
        },
        "system": {
            "hostname": "hybs",
            "metric": "foobar",
            "name": "Linux",
            "os_name": "18.04 LTS (Bionic Beaver)",
            "os_version": "Ubuntu",
            "test-id": 0,
            "test-name": "memory-cache-test-all",
            "username": "jan-hybs:1000:1000"
        },
        "timers": [
            {
                "duration": 1.46717154979706,
                "name": "mem_l1"
            },
            {
                "duration": 3.92046904563904,
                "name": "mem_l2"
            },
            {
                "duration": 7.61944723129272,
                "name": "mem_l3"
            }
        ]
    },
    {
        "_id": "5b5ee497fa7f60591680d098",
        "libs": [
            {
                "branch": "master",
                "commit": "85e8b641566b01f0d42b98a5b7c638c3777cc4d7",
                "datetime": "2018/07/30-12:11:00",
                "name": "bench-stat",
                "timestamp": 1532945460
            }
        ],
        "problem": {
            "application": "bench-stat",
            "case-name": "cache",
            "test-name": "memory"
        },
        "result": {
            "duration": 13.0979251861572
        },
        "system": {
            "hostname": "hybs",
            "metric": "foobar",
            "name": "Linux",
            "os_name": "18.04 LTS (Bionic Beaver)",
            "os_version": "Ubuntu",
            "test-id": 0,
            "test-name": "memory-cache-test-all",
            "username": "jan-hybs:1000:1000"
        },
        "timers": [
            {
                "duration": 1.46860754489899,
                "name": "mem_l1"
            },
            {
                "duration": 3.92684531211853,
                "name": "mem_l2"
            },
            {
                "duration": 7.70246124267578,
                "name": "mem_l3"
            }
        ]
    },
    {
        "_id": "5b5ee4a5fa7f60591680d099",
        "libs": [
            {
                "branch": "master",
                "commit": "85e8b641566b01f0d42b98a5b7c638c3777cc4d7",
                "datetime": "2018/07/30-12:11:00",
                "name": "bench-stat",
                "timestamp": 1532945460
            }
        ],
        "problem": {
            "application": "bench-stat",
            "case-name": "cache",
            "test-name": "memory"
        },
        "result": {
            "duration": 13.0920505523682
        },
        "system": {
            "hostname": "hybs",
            "metric": "foobar",
            "name": "Linux",
            "os_name": "18.04 LTS (Bionic Beaver)",
            "os_version": "Ubuntu",
            "test-id": 0,
            "test-name": "memory-cache-test-all",
            "username": "jan-hybs:1000:1000"
        },
        "timers": [
            {
                "duration": 1.47536301612854,
                "name": "mem_l1"
            },
            {
                "duration": 3.92514777183533,
                "name": "mem_l2"
            },
            {
                "duration": 7.69152879714966,
                "name": "mem_l3"
            }
        ]
    },
    {
        "_id": "5b5ee4b2fa7f60591680d09a",
        "libs": [
            {
                "branch": "master",
                "commit": "85e8b641566b01f0d42b98a5b7c638c3777cc4d7",
                "datetime": "2018/07/30-12:11:00",
                "name": "bench-stat",
                "timestamp": 1532945460
            }
        ],
        "problem": {
            "application": "bench-stat",
            "case-name": "cache",
            "test-name": "memory"
        },
        "result": {
            "duration": 13.1133403778076
        },
        "system": {
            "hostname": "hybs",
            "metric": "foobar",
            "name": "Linux",
            "os_name": "18.04 LTS (Bionic Beaver)",
            "os_version": "Ubuntu",
            "test-id": 0,
            "test-name": "memory-cache-test-all",
            "username": "jan-hybs:1000:1000"
        },
        "timers": [
            {
                "duration": 1.47022521495819,
                "name": "mem_l1"
            },
            {
                "duration": 3.92892837524414,
                "name": "mem_l2"
            },
            {
                "duration": 7.71417570114136,
                "name": "mem_l3"
            }
        ]
    },
    {
        "_id": "5b5ee6e4fa7f605a97263b86",
        "libs": [
            {
                "branch": "master",
                "commit": "c2c5434853e6c1c712b363bec9805dfefe6d7bb6",
                "datetime": "2018/07/30-12:21:54",
                "name": "bench-stat",
                "timestamp": 1532946114
            }
        ],
        "problem": {
            "application": "bench-stat",
            "case-name": "cache",
            "test-name": "memory"
        },
        "result": {
            "duration": 12.6670074462891
        },
        "system": {
            "hostname": "hybs",
            "metric": "foobar",
            "name": "Linux",
            "os_name": "18.04 LTS (Bionic Beaver)",
            "os_version": "Ubuntu",
            "test-id": 0,
            "test-name": "memory-cache-test-all",
            "username": "jan-hybs:1000:1000"
        },
        "timers": [
            {
                "duration": 1.46369588375092,
                "name": "mem_l1"
            },
            {
                "duration": 3.49426221847534,
                "name": "mem_l2"
            },
            {
                "duration": 7.70903825759888,
                "name": "mem_l3"
            }
        ]
    },
    {
        "_id": "5b5ee6f0fa7f605a97263b87",
        "libs": [
            {
                "branch": "master",
                "commit": "c2c5434853e6c1c712b363bec9805dfefe6d7bb6",
                "datetime": "2018/07/30-12:21:54",
                "name": "bench-stat",
                "timestamp": 1532946114
            }
        ],
        "problem": {
            "application": "bench-stat",
            "case-name": "cache",
            "test-name": "memory"
        },
        "result": {
            "duration": 12.6605281829834
        },
        "system": {
            "hostname": "hybs",
            "metric": "foobar",
            "name": "Linux",
            "os_name": "18.04 LTS (Bionic Beaver)",
            "os_version": "Ubuntu",
            "test-id": 0,
            "test-name": "memory-cache-test-all",
            "username": "jan-hybs:1000:1000"
        },
        "timers": [
            {
                "duration": 1.47359812259674,
                "name": "mem_l1"
            },
            {
                "duration": 3.48696994781494,
                "name": "mem_l2"
            },
            {
                "duration": 7.69994831085205,
                "name": "mem_l3"
            }
        ]
    },
    {
        "_id": "5b5ee6fdfa7f605a97263b88",
        "libs": [
            {
                "branch": "master",
                "commit": "c2c5434853e6c1c712b363bec9805dfefe6d7bb6",
                "datetime": "2018/07/30-12:21:54",
                "name": "bench-stat",
                "timestamp": 1532946114
            }
        ],
        "problem": {
            "application": "bench-stat",
            "case-name": "cache",
            "test-name": "memory"
        },
        "result": {
            "duration": 12.6351118087769
        },
        "system": {
            "hostname": "hybs",
            "metric": "foobar",
            "name": "Linux",
            "os_name": "18.04 LTS (Bionic Beaver)",
            "os_version": "Ubuntu",
            "test-id": 0,
            "test-name": "memory-cache-test-all",
            "username": "jan-hybs:1000:1000"
        },
        "timers": [
            {
                "duration": 1.45796549320221,
                "name": "mem_l1"
            },
            {
                "duration": 3.50020146369934,
                "name": "mem_l2"
            },
            {
                "duration": 7.67693424224854,
                "name": "mem_l3"
            }
        ]
    },
    {
        "_id": "5b5ee70afa7f605a97263b89",
        "libs": [
            {
                "branch": "master",
                "commit": "c2c5434853e6c1c712b363bec9805dfefe6d7bb6",
                "datetime": "2018/07/30-12:21:54",
                "name": "bench-stat",
                "timestamp": 1532946114
            }
        ],
        "problem": {
            "application": "bench-stat",
            "case-name": "cache",
            "test-name": "memory"
        },
        "result": {
            "duration": 12.6848621368408
        },
        "system": {
            "hostname": "hybs",
            "metric": "foobar",
            "name": "Linux",
            "os_name": "18.04 LTS (Bionic Beaver)",
            "os_version": "Ubuntu",
            "test-id": 0,
            "test-name": "memory-cache-test-all",
            "username": "jan-hybs:1000:1000"
        },
        "timers": [
            {
                "duration": 1.45765388011932,
                "name": "mem_l1"
            },
            {
                "duration": 3.49236631393433,
                "name": "mem_l2"
            },
            {
                "duration": 7.73483085632324,
                "name": "mem_l3"
            }
        ]
    },
    {
        "_id": "5b5ee716fa7f605a97263b8a",
        "libs": [
            {
                "branch": "master",
                "commit": "c2c5434853e6c1c712b363bec9805dfefe6d7bb6",
                "datetime": "2018/07/30-12:21:54",
                "name": "bench-stat",
                "timestamp": 1532946114
            }
        ],
        "problem": {
            "application": "bench-stat",
            "case-name": "cache",
            "test-name": "memory"
        },
        "result": {
            "duration": 12.6347560882568
        },
        "system": {
            "hostname": "hybs",
            "metric": "foobar",
            "name": "Linux",
            "os_name": "18.04 LTS (Bionic Beaver)",
            "os_version": "Ubuntu",
            "test-id": 0,
            "test-name": "memory-cache-test-all",
            "username": "jan-hybs:1000:1000"
        },
        "timers": [
            {
                "duration": 1.47831499576569,
                "name": "mem_l1"
            },
            {
                "duration": 3.49040341377258,
                "name": "mem_l2"
            },
            {
                "duration": 7.66602659225464,
                "name": "mem_l3"
            }
        ]
    },
    {
        "_id": "5b5ee723fa7f605a97263b8b",
        "libs": [
            {
                "branch": "master",
                "commit": "c2c5434853e6c1c712b363bec9805dfefe6d7bb6",
                "datetime": "2018/07/30-12:21:54",
                "name": "bench-stat",
                "timestamp": 1532946114
            }
        ],
        "problem": {
            "application": "bench-stat",
            "case-name": "cache",
            "test-name": "memory"
        },
        "result": {
            "duration": 12.627781867981
        },
        "system": {
            "hostname": "hybs",
            "metric": "foobar",
            "name": "Linux",
            "os_name": "18.04 LTS (Bionic Beaver)",
            "os_version": "Ubuntu",
            "test-id": 0,
            "test-name": "memory-cache-test-all",
            "username": "jan-hybs:1000:1000"
        },
        "timers": [
            {
                "duration": 1.47029304504395,
                "name": "mem_l1"
            },
            {
                "duration": 3.48535633087158,
                "name": "mem_l2"
            },
            {
                "duration": 7.67212152481079,
                "name": "mem_l3"
            }
        ]
    },
    {
        "_id": "5b5ee730fa7f605a97263b8c",
        "libs": [
            {
                "branch": "master",
                "commit": "c2c5434853e6c1c712b363bec9805dfefe6d7bb6",
                "datetime": "2018/07/30-12:21:54",
                "name": "bench-stat",
                "timestamp": 1532946114
            }
        ],
        "problem": {
            "application": "bench-stat",
            "case-name": "cache",
            "test-name": "memory"
        },
        "result": {
            "duration": 12.697114944458
        },
        "system": {
            "hostname": "hybs",
            "metric": "foobar",
            "name": "Linux",
            "os_name": "18.04 LTS (Bionic Beaver)",
            "os_version": "Ubuntu",
            "test-id": 0,
            "test-name": "memory-cache-test-all",
            "username": "jan-hybs:1000:1000"
        },
        "timers": [
            {
                "duration": 1.48340058326721,
                "name": "mem_l1"
            },
            {
                "duration": 3.48957252502441,
                "name": "mem_l2"
            },
            {
                "duration": 7.72413110733032,
                "name": "mem_l3"
            }
        ]
    }
]